commonvars/__init__.py
commonvars/py.typed
commonvars-0.4.2.dist-info/LICENSE
commonvars-0.4.2.dist-info/METADATA
commonvars-0.4.2.dist-info/WHEEL
commonvars-0.4.2.dist-info/RECORD
