Metadata-Version: 2.1
Name: commonvars
Version: 0.4.2
Summary: A simple & straight-forward Python module for creating context-dependent proxy objects.
Home-page: https://github.com/bswck/commonvars
Author: bswck
Author-email: bswck.dev@gmail.com
Requires-Python: >=3.8,<4.0
Classifier: Programming Language :: Python :: 3
Classifier: Programming Language :: Python :: 3.8
Classifier: Programming Language :: Python :: 3.9
Classifier: Programming Language :: Python :: 3.10
Classifier: Programming Language :: Python :: 3.11
